{
  "Cheese": [
    {
      "MaskNo": 0,
      "MaskType": 0,
      "Type": 0
    },
    {
      "MaskNo": 0,
      "MaskType": 1,
      "Type": 0
    },
    {
      "MaskNo": 0,
      "MaskType": 2,
      "Type": 0
    },
    {
      "MaskNo": 0,
      "MaskType": 3,
      "Type": 0
    },
    {
      "MaskNo": 0,
      "MaskType": 4,
      "Type": 0
    },
    {
      "MaskNo": 0,
      "MaskType": 5,
      "Type": 0
    },
    {
      "MaskNo": 0,
      "MaskType": 6,
      "Type": 0
    },
    {
      "MaskNo": 0,
      "MaskType": 7,
      "Type": 0
    }
  ],
  "Ingredients": [
    {
      "Position": {
        "x": 0.857177734375,
        "y": -53.0
      },
      "Rotation": 0.0,
      "Type": 42
    },
    {
      "Position": {
        "x": 48.857177734375,
        "y": 3.0
      },
      "Rotation": 4.974188804626465,
      "Type": 45
    },
    {
      "Position": {
        "x": 35.857177734375,
        "y": 33.0
      },
      "Rotation": 0.8726645112037659,
      "Type": 43
    },
    {
      "Position": {
        "x": -42.142822265625,
        "y": -32.0
      },
      "Rotation": 5.4977874755859375,
      "Type": 43
    },
    {
      "Position": {
        "x": 38.857177734375,
        "y": -37.0
      },
      "Rotation": 5.4977874755859375,
      "Type": 44
    },
    {
      "Position": {
        "x": 9.857177734375,
        "y": -25.0
      },
      "Rotation": 0.0,
      "Type": 43
    },
    {
      "Position": {
        "x": -22.142822265625,
        "y": -9.0
      },
      "Rotation": 0.0,
      "Type": 44
    },
    {
      "Position": {
        "x": 21.857177734375,
        "y": 11.0
      },
      "Rotation": 0.0,
      "Type": 42
    },
    {
      "Position": {
        "x": -17.142822265625,
        "y": 28.0
      },
      "Rotation": 0.0,
      "Type": 45
    },
    {
      "Position": {
        "x": -4.142822265625,
        "y": 57.0
      },
      "Rotation": 0.7853980660438538,
      "Type": 42
    },
    {
      "Position": {
        "x": -53.142822265625,
        "y": 0.0
      },
      "Rotation": 0.0,
      "Type": 45
    },
    {
      "Position": {
        "x": -47.142822265625,
        "y": 32.0
      },
      "Rotation": 0.0,
      "Type": 44
    },
    {
      "Position": {
        "x": 15.857177734375,
        "y": -51.0
      },
      "Rotation": 0.0,
      "Type": 58
    },
    {
      "Position": {
        "x": -41.142822265625,
        "y": -19.0
      },
      "Rotation": 0.2617993950843811,
      "Type": 58
    },
    {
      "Position": {
        "x": 17.857177734375,
        "y": 39.0
      },
      "Rotation": 0.8726645112037659,
      "Type": 58
    },
    {
      "Position": {
        "x": -51.142822265625,
        "y": 20.0
      },
      "Rotation": 2.7925264835357666,
      "Type": 58
    },
    {
      "Position": {
        "x": -4.142822265625,
        "y": 2.0
      },
      "Rotation": 6.108652591705322,
      "Type": 58
    },
    {
      "Position": {
        "x": 28.857177734375,
        "y": -15.0
      },
      "Rotation": 0.4363322854042053,
      "Type": 58
    },
    {
      "Position": {
        "x": 59.857177734375,
        "y": 24.0
      },
      "Rotation": 0.1745329350233078,
      "Type": 58
    },
    {
      "Position": {
        "x": -20.142822265625,
        "y": -48.0
      },
      "Rotation": 1.5707961320877075,
      "Type": 58
    },
    {
      "Position": {
        "x": -26.142822265625,
        "y": 8.0
      },
      "Rotation": 0.0,
      "Type": 58
    },
    {
      "Position": {
        "x": 54.857177734375,
        "y": -30.0
      },
      "Rotation": 0.6108651757240295,
      "Type": 58
    },
    {
      "Position": {
        "x": -4.142822265625,
        "y": -25.0
      },
      "Rotation": 1.8325954675674438,
      "Type": 58
    },
    {
      "Position": {
        "x": 31.857177734375,
        "y": 61.0
      },
      "Rotation": 3.141592264175415,
      "Type": 58
    },
    {
      "Position": {
        "x": -20.142822265625,
        "y": 57.0
      },
      "Rotation": 0.8726645112037659,
      "Type": 58
    },
    {
      "Position": {
        "x": -44.142822265625,
        "y": 45.0
      },
      "Rotation": 3.6651909351348877,
      "Type": 58
    }
  ]
}
